<annotation>
	<folder>photo</folder>
	<filename>12_5.tif</filename>
	<path>C:\Users\julyfire\Desktop\遥感影像地学解译\faster-rcnn-pytorch-master\LandSlideDataSet\photo\12_5.tif</path>
	<source>
		<database>Unknown</database>
	</source>
	<size>
		<width>858</width>
		<height>741</height>
		<depth>3</depth>
	</size>
	<segmented>0</segmented>
	<object>
		<name>slide</name>
		<pose>Unspecified</pose>
		<truncated>0</truncated>
		<difficult>0</difficult>
		<bndbox>
			<xmin>352</xmin>
			<ymin>459</ymin>
			<xmax>769</xmax>
			<ymax>662</ymax>
		</bndbox>
	</object>
	<object>
		<name>slide</name>
		<pose>Unspecified</pose>
		<truncated>0</truncated>
		<difficult>0</difficult>
		<bndbox>
			<xmin>9</xmin>
			<ymin>118</ymin>
			<xmax>538</xmax>
			<ymax>451</ymax>
		</bndbox>
	</object>
</annotation>
