<annotation>
	<folder>photo</folder>
	<filename>8_3.tif</filename>
	<path>C:\Users\julyfire\Desktop\遥感影像地学解译\faster-rcnn-pytorch-master\LandSlideDataSet\photo\8_3.tif</path>
	<source>
		<database>Unknown</database>
	</source>
	<size>
		<width>725</width>
		<height>676</height>
		<depth>3</depth>
	</size>
	<segmented>0</segmented>
	<object>
		<name>slide</name>
		<pose>Unspecified</pose>
		<truncated>0</truncated>
		<difficult>0</difficult>
		<bndbox>
			<xmin>205</xmin>
			<ymin>97</ymin>
			<xmax>643</xmax>
			<ymax>636</ymax>
		</bndbox>
	</object>
</annotation>
